freedom_utils/__init__.py
freedom_utils/decorators.py
freedom_utils/helpers.py
freedom_utils/wfile.py
freedom_utils/winput.py
freedom_utils/wlog.py
freedom_utils/wmath.py
freedom_utils/wtime.py
tests/__init__.py
tests/test_wmath.py
tests/test_wtime.py
freedom_utils-0.0.2.dist-info/LICENSE
freedom_utils-0.0.2.dist-info/METADATA
freedom_utils-0.0.2.dist-info/WHEEL
freedom_utils-0.0.2.dist-info/top_level.txt
freedom_utils-0.0.2.dist-info/RECORD
