Metadata-Version: 2.1
Name: freedom-utils
Version: 0.0.2
Summary: dev utils, help developer coding, then have more freedom
Home-page: https://github.com/wujunwei928/freedom_utils
Author: wujunwei
Author-email: 1399952803@qq.com
License: MIT Licence
Keywords: dev tools,dev utils
Platform: any
Requires-Python: >=3.7
License-File: LICENSE
Requires-Dist: inquirer (~=2.10.1)
Requires-Dist: setuptools (~=61.2.0)
Requires-Dist: numpy (~=1.21.5)
